{
  "user": [{
      "name": "Alvin Phan",
      "username": "phanalvin1",
      "password": "turtwigBestPokemon98",
      "club": [
          "cs187Main",
          "cs187Frontend"
      ]
    },
    {
      "name": "Anthony Orciuoli",
      "username": "orciuoliAnthony1",
      "password": "admin",
      "club": [
        "cs187Main",
        "cs187Frontend"
      ]
    },
    {
      "name": "Shalin Avlani",
      "username": "avlaniShalin1",
      "password": "admin",
      "club": [
          "cs187Main",
          "cs187Backend"
      ]
    },
    {
      "name": "Kevin Lee",
      "username": "leeKevin1",
      "password": "admin",
      "club": [
          "cs187Main",
          "cs187Backend"
      ]
    }],

  "club": [{
      "name": "Computer Science 187",
      "clubCode": "cs187Main",
      "addCode": "",
      "member": [{
          "username": "phanalvin1",
          "rank": "co-founder"
      },
      {
          "username": "orciuoliAnthony1",
          "rank": "co-founder"
      },
      {
        "username": "avlaniShalin1",
        "rank": "founder"
      },
      {
        "username": "leeKevin1",
        "rank": "co-founder"
      }]
  },

  {
    "name": "Frontend - CS 187",
    "clubCode": "cs187Frontend",
    "addCode": "",
    "member": [{
        "username": "phanalvin1",
        "rank": "founder"
    },
    {
        "username": "orciuoliAnthony1",
        "rank": "founder"
    }]
  },

  {
    "name": "Backend - CS 187",
    "clubCode": "cs187Backend",
    "addCode": "",
    "member": [{
        "username": "avlaniShalin1",
        "rank": "founder"
    },
    {
      "username": "leeKevin1",
      "rank": "founder"
    }]
  }]

}
